treqs/__init__.py
treqs-0.0.2.dist-info/METADATA
treqs-0.0.2.dist-info/WHEEL
treqs-0.0.2.dist-info/top_level.txt
treqs-0.0.2.dist-info/RECORD
