Metadata-Version: 2.4
Name: treqs
Version: 0.0.2
Summary: TReqs package
Author-email: TReqs <support@treqs.ai>
License: MIT
Requires-Python: >=3.8
